Workbook

Sheet Sheet1
C1: P/E | D1: EV/EBITDA | E1: P/BV | F1: CURRENT PRICE | G1: P/S | H1: ROE | I1: Debt/Equity | J1: Interest Coverage | K1: Net Profit Margin | L1: PEG | M1: Div Yield | N1: ROCE
B2: SECTORS
B3: FMCG
B5: Hindustan Unilever | C5: 54.5 | D5: 36.7 | E5: 11.8 | F5: 2457 | G5: 8.99 | H5: 0.207 | I5: =30461/49402 -> 0.61659447 | J5: 36 | K5: 0.17 | L5: =C5/(-0.17*H5) -> -1548.7354 | M5: 0.0174 | N5: 0.278
B6: ITC | C6: 25.1 | D6: 17.2 | E6: 7.09 | F6: 403 | G6: 6.43 | H6: 0.273 | I6: 0.28 | J6: =492.58 -> 492.58 | K6: 0.45 | L6: =C6/(48%*H6) -> 191.54457 | M6: 0.0355 | N6: 0.3679
B7: Nestlé India | C7: 82.1 | D7: 50.8 | E7: 53.9 | F7: 1275 | G7: 11.7 | H7: 0.83 | I7: 1.99 | J7: 32.86 | K7: 0.14 | L7: =C7/(H7*21%) -> 471.02697 | M7: 0.0107 | N7: 0.957
B8: Varun Beverages | C8: 53 | D8: 29.8 | E8: 8.56 | F8: 466 | G8: 7.44 | H8: 0.225 | I8: 0.346 | J8: 26.44 | K8: 0.14 | L8: =C8/(H8*87%) -> 270.75351 | M8: 0.0021 | N8: 0.248
B9: Britannia Industries | C9: 61 | D9: 39.9 | E9: 37.8 | F9: 5860 | G9: 7.63 | H9: 0.529 | I9: 1.53 | J9: 26.84 | K9: 0.125 | L9: =C9/(H9*17%) -> 678.30535 | M9: 0.0128 | N9: 0.5299
B10: Godrej Consumer | C10: 62.4 | D10: 37.1 | E10: 9.64 | F10: 1147 | G10: 7.9 | H10: 0.152 | I10: 0.64 | J10: 9.365 | K10: 0.12 | L10: =C10/(H10*-0.38) -> -1080.3324 | M10: 0.0131 | N10: 0.192
B11: Tata Consumer Products | C11: 11 | D11: 44.5 | E11: 5.72 | F11: 1184 | G11: 6.24 | H11: 0.0701 | I11: 0.576 | J11: 18.6 | K11: 0.073 | L11: =C11/(36%*H11) -> 435.88524 | M11: 0.007 | N11: 0.0916
B12: United Spirits | C12: 61.6 | D12: 38.4 | E12: 12.6 | F12: 1451 | G12: 8.34 | H12: 0.197 | I12: 0.6 | J12: 23.25 | K12: 0.129 | L12: =C12/(H12*45%) -> 694.86746 | M12: 0.0083 | N12: 0.265
B13: Marico | C13: 56.5 | D13: 39.3 | E13: 23.2 | F13: 725 | G13: 7.67 | H13: 0.413 | I13: 1.14 | J13: 50.94 | K13: 0.138 | L13: =C13/(H13*17%) -> 804.72867 | M13: 0.0146 | N13: 0.452
B14: Dabur India | C14: 50.8 | D14: 31.7 | E14: 8.38 | F14: 518 | G14: 7.19 | H14: 0.17 | I14: 0.52 | J14: 17.84 | K14: 0.139 | L14: =C14/(20%*H14) -> 1494.1176 | M14: 0.0155 | N14: 0.202
B16: IT
B18: TCS (Tata Consultancy Services) | C18: 22.67 | D18: 15.4 | E18: 10.8 | F18: 3152 | G18: 4.43 | H18: 0.524 | I18: 0.65 | J18: 84.06 | K18: 0.19 | L18: =C18/(6%*H18) -> 721.05598 | M18: 0.0191 | N18: 0.646
B19: Infosys | C19: 23.1 | D19: 14 | E19: 6.27 | F19: 1561 | G19: 3.83 | H19: 0.288 | I19: 0.55 | J19: 109.4 | K19: 0.166 | L19: =C19/(33%*H19) -> 243.05556 | M19: 0.0276 | N19: 0.375
B20: HCL Technologies | C20: 26 | D20: 15.3 | E20: 6.17 | F20: 1624 | G20: 3.6 | H20: 0.25 | I20: 0.523 | J20: 40.4 | K20: 0.14 | L20: =C20/(H20*6%) -> 1733.3333 | M20: 0.0332 | N20: 0.316
B21: Wipro | C21: 19.4 | D21: 12 | E21: 3.04 | F21: 250 | G21: 2.92 | H21: 0.166 | I21: 0.53 | J21: 13.57 | K21: 0.15 | L21: =C21/(52%*H21) -> 224.74513 | M21: 0.024 | N21: 0.195
B22: LTIMindtree | C22: 36.2 | D22: 22.1 | E22: 7.55 | F22: 5938 | G22: 4.44 | H22: 0.215 | I22: 0.39 | J22: 28.19 | K22: 0.12 | L22: =C22/(58%*H22) -> 290.29671 | M22: 0.0107 | N22: 0.276
B23: Tech Mahindra | C23: 33.1 | D23: 17.8 | E23: 5.39 | F23: 1515 | G23: 2.75 | H23: 0.146 | I23: 0.67 | J23: 30.37 | K23: 0.083 | L23: =C23/(H23*6%) -> 3778.5388 | M23: 0.0297 | N23: 0.186
B24: Persistent Systems | C24: 60.8 | D24: 38.9 | E24: 14 | F24: 6417 | G24: 7.66 | H24: 0.241 | I24: 0.38 | J24: 40.18 | K24: 0.126 | L24: =C24/(61%*H24) -> 413.57731 | M24: 0.0055 | N24: 0.304
B25: Oracle Financial Services Software (OFSS) | C25: 29.9 | D25: 19.6 | E25: 9.62 | F25: 8153 | G25: 10 | H25: 0.293 | I25: 0.263 | J25: -393.5 | K25: 0.34 | L25: =C25/(3%*H25) -> 3401.5927 | M25: 0.0327 | N25: 0.406
B26: Coforge | C26: 56.2 | D26: 26.7 | E26: 9.26 | F26: 1910 | G26: 4.46 | H26: 0.16 | I26: 0.97 | J26: 17.88 | K26: 0.094 | L26: =C26/(37%*H26) -> 949.32432 | M26: 0.008 | N26: 0.203
B27: Mphasis | C27: 29.9 | D27: 17.4 | E27: 5.57 | F27: 2801 | G27: 3.58 | H27: 0.182 | I27: 0.69 | J27: 20.7 | K27: 0.12 | L27: =C27/(36%*H27) -> 456.34921 | M27: 0.0203 | N27: 0.227
B29: Banking & Financials
B31: HDFC Bank | C31: 21.5 | D31: 16.9 | E31: 2.86 | F31: 1012 | G31: 4.5 | H31: 0.144 | I31: 7.37 | J31: 0.78 | K31: 0.22 | L31: =C31/(76%*H31) -> 196.45468 | M31: 0.0109 | N31: 0.0751
B32: ICICI Bank | C32: 18.6 | D32: 16.6 | E32: 2.97 | F32: 1387 | G32: 5.15 | H32: 0.179 | I32: 7.06 | J32: 0.6 | K32: 0.296 | L32: =C32/(85%*H32) -> 122.24778 | M32: 0.0079 | N32: 0.0787
B33: State Bank of India (SBI) | C33: 11.5 | D33: 16.5 | E33: 1.61 | F33: 975 | G33: 1.78 | H33: 0.172 | I33: 12.48 | J33: 0.75 | K33: 0.166 | L33: =C33/(82%*H33) -> 81.537153 | M33: 0.0162 | N33: 0.0647
B34: Bajaj Finance | C34: 35.3 | D34: 19.8 | E34: 6.24 | F34: 1040 | G34: 8.5 | H34: 0.192 | I34: 3.94 | J34: 1.98 | K34: 0.24 | L34: =C34/(79%*H34) -> 232.72679 | M34: 0.0042 | N34: 0.114
B35: Life Insurance Corporation of India | C35: 11.1 | D35: 8.94 | E35: 4 | F35: 895 | G35: 0.62 | H35: 0.457 | I35: 40.65 | J35: - | K35: 0.06 | L35: =C35/(84%*H35) -> 28.915286 | M35: 0.0134 | N35: 0.531
B36: Kotak Mahindra Bank | C36: 22.8 | D36: 18.5 | E36: 2.5 | F36: 2127 | G36: 6.23 | H36: 0.154 | I36: 4.44 | J36: 0.65 | K36: 0.27 | L36: =C36/(98%*H36) -> 151.07342 | M36: 0.0012 | N36: 0.0817
B37: Axis Bank | C37: 15.4 | D37: 16.6 | E37: 2.03 | F37: 1289 | G37: 3.09 | H37: 0.163 | I37: 77.26 | J37: 1.066 | K37: 0.2 | L37: =C37/(99%*H37) -> 95.432856 | M37: 0.0008 | N37: 0.0711
B38: Bajaj Finserv | C38: 34.8 | D38: 13.4 | E38: 4.43 | F38: 2105 | G38: 2.38 | H38: 0.134 | I38: 8.25 | J38: 2.07 | K38: 0.14 | L38: =C38/(98%*H38) -> 265.00152 | M38: 0.0005 | N38: 0.11
B39: SBI Life Insurance | C39: 82.1 | D39: 74.5 | E39: 11 | F39: 2009 | G39: 1.94 | H39: 0.151 | I39: 25.78 | J39: - | K39: 0.02 | L39: =C39/(89%*H39) -> 610.90855 | M39: 0.0014 | N39: 0.169
B40: Jio Financial Services | C40: 121 | D40: 92.4 | E40: 1.46 | F40: 307 | G40: 77.2 | H40: 0.0123 | I40: 0.13 | J40: 7.5 | K40: 0.65 | L40: =C40/(80%*H40) -> 12296.748 | M40: 0.0016 | N40: 0.0147
B42: Pharma & HEALTHCARE
B44: Sun Pharma Industries | C44: 37.6 | D44: 23 | E44: 5.57 | F44: 1812 | G44: 7.91 | H44: 0.169 | I44: 0.33 | J44: 69.86 | K44: 0.19 | L44: =C44/(65%*H44) -> 342.28493 | M44: 0.0087 | N44: 0.202
B45: Divi’s Laboratories | C45: 69 | D45: 45.7 | E45: 11.2 | F45: 6455 | G45: 17.1 | H45: 0.154 | I45: 0.18 | J45: 306.42 | K45: 0.25 | L45: =C45/(64%*H45) -> 700.08117 | M45: 0.0046 | N45: 0.204
B46: Torrent Pharma | C46: 58.2 | D46: 32.5 | E46: 14.9 | F46: 3726 | G46: 10.3 | H46: 0.265 | I46: 0.84 | J46: 22.11 | K46: 0.17 | L46: =C46/(43%*H46) -> 510.75033 | M46: 0.0086 | N46: 0.27
B47: Cipla | C47: 22.6 | D47: 14.9 | E47: 3.75 | F47: 1525 | G47: 4.35 | H47: 0.178 | I47: 0.22 | J47: 148.91 | K47: 0.19 | L47: =C47/(75%*H47) -> 169.28839 | M47: 0.0085 | N47: 0.227
B48: Dr. Reddy’s Laboratories | C48: 18 | D48: 11 | E48: 2.92 | F48: 1244 | G48: 3.03 | H48: 0.18 | I48: 0.51 | J48: 32.18 | K48: 0.17 | L48: =C48/(88%*H48) -> 113.63636 | M48: 0.0064 | N48: 0.227
B49: Zydus Lifesciences | C49: 18.7 | D49: 12.6 | E49: 3.68 | F49: 934 | G49: 3.84 | H49: 0.212 | I49: 0.85 | J49: 29.24 | K49: 0.21 | L49: =C49/(76%*H49) -> 116.06256 | M49: 0.0117 | N49: 0.243
B50: Lupin | C50: 21.8 | D50: 13.9 | E50: 4.85 | F50: 2072 | G50: 3.82 | H50: 0.206 | I50: 0.71 | J50: 22.54 | K50: 0.17 | L50: =C50/(83%*H50) -> 127.50029 | M50: 0.0058 | N50: 0.213
B51: Mankind Pharma | C51: 52.8 | D51: 26.5 | E51: 6.05 | F51: 2238 | G51: 6.82 | H51: 0.147 | I51: 0.88 | J51: 5.48 | K51: 0.131 | L51: =C51/(100%*H51) -> 359.18367 | M51: 0.0004 | N51: 0.16
B52: Max Healthcare | C52: 80.2 | D52: 51.3 | E52: 11.2 | F52: 1162 | G52: 14.2 | H52: 0.127 | I52: 0.62 | J52: 11.67 | K52: 0.17 | L52: =C52/(86%*H52) -> 734.29775 | M52: 0.0013 | N52: 0.149
B53: Apollo Hospitals | C53: 63.2 | D53: 31.4 | E53: 11.6 | F53: 7356 | G53: 4.55 | H53: 0.184 | I53: 1.41 | J53: 9.38 | K53: 0.07 | L53: =C53/(87%*H53) -> 394.8026 | M53: 0.0026 | N53: 0.166
B55: Auto
B57: Maruti Suzuki | C57: 34.1 | D57: 19.9 | E57: 5.06 | F57: 16031 | G57: 3.14 | H57: 0.159 | I57: 0.39 | J57: 130.2 | K57: 0.09 | L57: =C57/(71%*H57) -> 302.06396 | M57: 0.0085 | N57: 0.217
B58: Mahindra & Mahindra (M&M) | C58: 32 | D58: 14.9 | E58: 5.5 | F58: 3670 | G58: 2.6 | H58: 0.18 | I58: 2.54 | J58: 4.2 | K58: 0.09 | L58: =C58/(78%*H58) -> 227.92023 | M58: 0.0067 | N58: 0.139
B59: Bajaj Auto | C59: 30.4 | D59: 21.5 | E59: 7.35 | F59: 9050 | G59: 4.62 | H59: 0.228 | I59: 0.91 | J59: 14.38 | K59: 0.15 | L59: =C59/(20%*H59) -> 666.66667 | M59: 0.0231 | N59: 0.281
B60: Eicher Motors | C60: 37.6 | D60: 26.2 | E60: 8.73 | F60: 7007 | G60: 8.97 | H60: 0.241 | I60: 0.31 | J60: 94.5 | K60: 0.24 | L60: =C60/(59%*H60) -> 264.43491 | M60: 0.0099 | N60: 0.298
B61: Hyundai Motor India | C61: 33.2 | D61: 18.6 | E61: 11 | F61: 2295 | G61: 2.79 | H61: 0.422 | I61: 0.8 | J61: 100.94 | K61: 0.084 | L61: =C61/(69%*H61) -> 114.01882 | M61: 0.009 | N61: 0.542
B62: TVS Motor Company | C62: 64 | D62: 23.9 | E62: 20.6 | F62: 3510 | G62: 3.41 | H62: 0.284 | I62: 5.4 | J62: 3.94 | K62: 0.057 | L62: =C62/(79%*H62) -> 285.25584 | M62: 0.0028 | N62: 0.154
B63: Tata Motors (Passenger Vehicles) | C63: 9.78 | D63: 4.08 | E63: 1.2 | F63: 360 | G63: 0.34 | H63: 0.281 | I63: 2.1 | J63: 15.8 | K63: 0.24 | L63: =C63/(92%*H63) -> 37.830729 | M63: 0.0168 | N63: 0.2
B64: Hero MotoCorp | C64: 23.1 | D64: 15.6 | E64: 5.87 | F64: 6113 | G64: 2.9 | H64: 0.231 | I64: 0.55 | J64: 92.77 | K64: 0.126 | L64: =C64/(25%*H64) -> 400 | M64: 0.0267 | N64: 0.303
B65: Samvardhana Motherson | C65: 36.3 | D65: 11.9 | E65: 3.32 | F65: 115 | G65: 1.04 | H65: 0.122 | I65: 1.71 | J65: 8.9 | K65: 0.03 | L65: =C65/(84%*H65) -> 354.21546 | M65: 0.0049 | N65: 0.137
B66: Bosch | C66: 47 | D66: 31.2 | E66: 7.61 | F66: 36158 | G66: 5.62 | H66: 0.156 | I66: 0.45 | J66: 143.15 | K66: 0.14 | L66: =C66/(25%*H66) -> 1205.1282 | M66: 0.0142 | N66: 0.211
B68: Energy
B70: NTPC | C70: 13.4 | D70: 8.73 | E70: 1.66 | F70: 328 | G70: 1.7 | H70: 0.121 | I70: 1.8 | J70: 5.4 | K70: 0.13 | L70: =C70/(65%*H70) -> 170.37508 | M70: 0.0256 | N70: 0.0995
B71: Adani Power | C71: 23.9 | D71: 13.9 | E71: 5.02 | F71: 149 | G71: 5.19 | H71: 0.261 | I71: 1.15 | J71: 7.4 | K71: 0.22 | L71: =C71/(100%*H71) -> 91.570881 | M71: 0 | N71: 0.225
B72: Power Grid Corporation | C72: 16.8 | D72: 9.56 | E72: 2.6 | F72: 274 | G72: 5.52 | H72: 0.17 | I72: 1.81 | J72: 6.1 | K72: 0.33 | L72: =C72/(46%*H72) -> 214.83376 | M72: 0.0333 | N72: 0.128
B73: Adani Green | C73: 77.2 | D73: 23.3 | E73: 8.62 | F73: 1027 | G73: 13.8 | H73: 0.146 | I73: 5.45 | J73: 2.21 | K73: 0.19 | L73: =C73/(100%*H73) -> 528.76712 | M73: 0 | N73: 0.087
B74: Tata Power Company | C74: 31 | D74: 11.8 | E74: 3.34 | F74: 392 | G74: 1.89 | H74: 0.11 | I74: 3.35 | J74: 3.51 | K74: 0.07 | L74: =C74/(80%*H74) -> 352.27273 | M74: 0.0058 | N74: 0.108
B75: Adani Energy Solutions | C75: 52.6 | D75: 19.3 | E75: 5.02 | F75: 987 | G75: 4.63 | H75: 0.136 | I75: 2.54 | J75: 2.75 | K75: 0.09 | L75: =C75/(100%*H75) -> 386.76471 | M75: 0 | N75: 0.102
B76: JSW Energy | C76: 41.8 | D76: 16.7 | E76: 2.94 | F76: 484 | G76: 5.3 | H76: 0.0741 | I76: 2.9 | J76: 2.6 | K76: 0.14 | L76: =C76/(82%*H76) -> 687.92996 | M76: 0.0041 | N76: 0.0649
B77: NTPC Green Energy | C77: 132 | D77: 41.1 | E77: 4.2 | F77: 94.9 | G77: 33 | H77: 0.0385 | I77: 1.58 | J77: 3.84 | K77: 0.25 | L77: =C77/(100%*H77) -> 3428.5714 | M77: 0 | N77: 0.0489
B78: NHPC | C78: 24.4 | D78: 15.8 | E78: 1.9 | F78: 76.8 | G78: 6.88 | H78: 0.0753 | I78: 1.7 | J78: 6.28 | K78: 0.32 | L78: =C78/(36%*H78) -> 900.10329 | M78: 0.0249 | N78: 0.0742
B79: Torrent Power | C79: 22.2 | D79: 13.4 | E79: 3.54 | F79: 1315 | G79: 2.31 | H79: 0.19 | I79: 1,14 | J79: 7.2 | K79: 0.11 | L79: =C79/(68%*H79) -> 171.82663 | M79: 0.0145 | N79: 0.16
B81: Metals
B83: Adani Enterprises | C83: 119 | D83: 25.1 | E83: 5.49 | F83: 2288 | G83: 3.18 | H83: 0.0982 | I83: 3.1 | J83: 2.74 | K83: 0.09 | L83: =C83/(98%*H83) -> 1236.5435 | M83: 0.0006 | N83: 0.0945
B84: JSW Steel | C84: 45.8 | D84: 13.5 | E84: 3.41 | F84: 1144 | G84: 1.6 | H84: 0.0494 | I84: 2.02 | J84: 4.09 | K84: 0.035 | L84: =C84/(76%*H84) -> 1219.902 | M84: 0.0024 | N84: 0.0811
B85: Tata Steel | C85: 28.6 | D85: 9.81 | E85: 2.24 | F85: 168 | G85: 0.95 | H85: 0.0389 | I85: 2.01 | J85: 5.5 | K85: 0.03 | L85: =C85/(-0.31*H85) -> -2371.6726 | M85: 0.0214 | N85: 0.0883
B86: Vedanta | C86: 16 | D86: 5.91 | E86: 5.01 | F86: 521 | G86: 1.29 | H86: 0.385 | I86: 4.39 | J86: 6.03 | K86: 0.11 | L86: =C86/(-0.13*H86) -> -319.68032 | M86: 0.0827 | N86: 0.253
B87: Hindustan Zinc | C87: 19.2 | D87: 11.5 | E87: 14.7 | F87: 476 | G87: 5.94 | H87: 0.724 | I87: 1.6 | J87: 20.5 | K87: 0.31 | L87: =C87/(-0.19*H87) -> -139.57546 | M87: 0.0598 | N87: 0.607
B88: Hindalco Industries | C88: 10.1 | D88: 6.79 | E88: 1.35 | F88: 804 | G88: 0.71 | H88: 0.14 | I88: 1.2 | J88: 12.8 | K88: 0.09 | L88: =C88/(93%*H88) -> 77.572965 | M88: 0.0062 | N88: 0.148
B89: Jindal Steel | C89: 29.4 | D89: 12.5 | E89: 2.17 | F89: 1036 | G89: 2.16 | H89: 0.0768 | I89: 0.85 | J89: 9.37 | K89: 0.06 | L89: =C89/(93%*H89) -> 411.62634 | M89: 0.0019 | N89: 0.107
B90: Lloyds Metals | C90: 36 | D90: 26.2 | E90: 8.39 | F90: 1229 | G90: 7.3 | H90: 0.314 | I90: 1.61 | J90: 13.57 | K90: 0.2 | L90: =C90/(96%*H90) -> 119.42675 | M90: 0.0008 | N90: 0.383
B91: NMDC | C91: 9.34 | D91: 5.6 | E91: 2.04 | F91: 74.4 | G91: 2.45 | H91: 0.2365 | I91: 0.31 | J91: 58.12 | K91: 0.26 | L91: =C91/(56%*H91) -> 70.522501 | M91: 0.0446 | N91: 0.296
B92: Jindal Stainless | C92: 29.4 | D92: 12.5 | E92: 2.17 | F92: 1036 | G92: 2.16 | H92: 0.0768 | I92: 1.16 | J92: 9.89 | K92: 0.07 | L92: =C92/(90%*H92) -> 425.34722 | M92: 0.0039 | N92: 0.182
B94: Media
B96: Sun TV Network | C96: 13.4 | D96: 7.49 | E96: 1.79 | F96: 561 | G96: 5.07 | H96: 0.157 | I96: 0.086 | J96: 185.75 | K96: 0.37 | L96: =C96/(65%*H96) -> 131.30818 | M96: 0.027 | N96: 0.204
B97: Prime Focus | C97: 111 | D97: 14.9 | E97: 7.68 | F97: 172 | G97: 3.37 | H97: -16.7 | I97: 4.55 | J97: 2.94 | K97: -0.11 | L97: =C97/(100%*H97) -> -6.6467066 | M97: 0 | N97: 0.0795
B98: PVR Inox | C98: - | D98: 8.7 | E98: 1.49 | F98: 1071 | G98: 1.68 | H98: -0.0418 | I98: 1.26 | J98: 3.96 | K98: -0.01 | L98: - | M98: 0 | N98: 0.0272
B99: Nazara Technolo. | C99: 10.9 | D99: 8.14 | E99: 2.76 | F99: 253 | G99: 4.5 | H99: 0.029 | I99: 0.25 | J99: 5.95 | K99: 0.02 | L99: =C99/(100%*H99) -> 375.86207 | M99: 0 | N99: 0.025
B100: Zee Entertainment | C100: 14.9 | D100: 7.65 | E100: 0.82 | F100: 98.8 | G100: 1.19 | H100: 0.0671 | I100: 0.18 | J100: 31.58 | K100: 0.07 | L100: =C100/(66%*H100) -> 336.44944 | M100: 0.0239 | N100: 0.0921
B101: Saregama India | C101: 37.7 | D101: 20.5 | E101: 4.52 | F101: 390 | G101: 6.47 | H101: 0.125 | I101: 0.36 | J101: 50.85 | K101: 0.175 | L101: =C101/(58%*H101) -> 520 | M101: 0.0113 | N101: 0.172
B102: Netrwk.18 Media | C102: 784 | D102: 22.4 | E102: 1.43 | F102: 45.4 | G102: 2.42 | H102: -0.0334 | I102: 0.8 | J102: 0.6 | K102: -0.43 | L102: =C102/(100%*H102) -> -23473.054 | M102: 0 | N102: 0.0061
B103: Tips Music | C103: 40.3 | D103: 29.6 | E103: 27.2 | F103: 548 | G103: 21 | H103: 0.829 | I103: 0.44 | J103: - | K103: 0.52 | L103: =C103/(46%*H103) -> 105.67997 | M103: 0.0145 | N103: 1.09
B104: D B Corp | C104: 13.4 | D104: 6.91 | E104: 2 | F104: 258 | G104: 1.95 | H104: 0.167 | I104: 0.36 | J104: 22.44 | K104: 0.15 | L104: =C104/(42%*H104) -> 191.04648 | M104: 0.0464 | N104: 0.211
B105: Jagran Prakashan Ltd | C105: 8.83 | D105: 5.55 | E105: 0.78 | F105: 70 | G105: 0.79 | H105: 0.0621 | I105: 0.45 | J105: 12.1 | K105: 0.07 | L105: - | M105: 0.0858 | N105: 0.0595
B107: Infrastructure
B109: Larsen & Toubro | C109: 35 | D109: 17.3 | E109: 5.56 | F109: 4087 | G109: 2.08 | H109: 0.166 | I109: 2.86 | J109: 3.9 | K109: 0.07 | L109: =C109/(69%*H109) -> 305.57011 | M109: 0.0084 | N109: 0.145
B110: Rail Vikas | C110: 59.4 | D110: 35.6 | E110: 7.03 | F110: 323 | G110: 3.36 | H110: 0.14 | I110: 1.07 | J110: 2.08 | K110: 0.06 | L110: =C110/(72%*H110) -> 589.28571 | M110: 0.0053 | N110: 0.147
B111: NBCC | C111: 47.4 | D111: 28.6 | E111: 11.9 | F111: 117 | G111: 2.48 | H111: 0.255 | I111: 4.01 | J111: - | K111: 0.05 | L111: =C111/(67%*H111) -> 277.43635 | M111: 0.0057 | N111: 0.332
B112: IRB Infra. Devl. | C112: 29.8 | D112: 11 | E112: 1.3 | F112: 43.2 | G112: 3.25 | H112: 0.0591 | I112: 1.67 | J112: 2.7 | K112: 0.82 | L112: =C112/(97%*H112) -> 519.82486 | M112: 0.007 | N112: 0.0782
B113: Kalpataru Proj. | C113: 25.2 | D113: 11.4 | E113: 2.94 | F113: 1213 | G113: 0.81 | H113: 0.0996 | I113: 2.8 | J113: 4.84 | K113: 0.03 | L113: =C113/(100%*H113) -> 253.01205 | M113: 0 | N113: 0.0106
B114: KEC International | C114: 27.4 | D114: 13.7 | E114: 3.32 | F114: 704 | G114: 0.8 | H114: 0.12 | I114: 3.18 | J114: 2.84 | K114: 0.03 | L114: =C114/(74%*H114) -> 308.55856 | M114: 0.008 | N114: 0.18
B115: Ircon Intl. | C115: 25.5 | D115: 13.2 | E115: 2.37 | F115: 163 | G115: 1.56 | H115: 0.113 | I115: 2.13 | J115: 3.12 | K115: 0.06 | L115: =C115/(66%*H115) -> 341.91472 | M115: 0.0165 | N115: 0.116
B116: Afcons Infrastr. | C116: 30 | D116: 9.58 | E116: 2.79 | F116: 410 | G116: 1.18 | H116: 0.111 | I116: 2.33 | J116: 2.95 | K116: 0.04 | L116: =C116/(81%*H116) -> 333.667 | M116: 0.0062 | N116: 0.196
B117: Techno Elec. Engg | C117: 31.6 | D117: 23.2 | E117: 3.64 | F117: 1211 | G117: 4.99 | H117: 0.128 | I117: 0.39 | J117: 25.18 | K117: 0.17 | L117: =C117/(75%*H117) -> 329.16667 | M117: 0.0075 | N117: 0.165
...

Sheet Sheet2
B1: NESTLE | C1: TCS | D1: LIC | E1: TORRENT | F1: HYUNDAI | G1: ADANI POWER | H1: HZNC | I1: DB Corp | J1: CEMI | K1: TATA COMM | L1: NIFTY | O1: Parameters | P1: NESTLE | Q1: TCS | R1: LIC | S1: TORRENT | T1: HYUNDAI | U1: ADANI POWER | V1: HZNC | W1: DB CORP | X1: CEMI | Y1: TATA COMM | Z1: NIFTY | AI1: HYUNDAI | AJ1: ADANI POWER | AK1: CEMI
A2: Date | B2: Change % | C2: Change % | D2: Change % | E2: Change % | F2: Change % | G2: Change % | H2: Change % | I2: Change % | J2: Change % | K2: Change % | L2: Change % | O2: Return | P2: =AVERAGE(B3:B271) -> 0.00047137546 | Q2: =AVERAGE(C3:C271) -> -0.00088773234 | R2: =AVERAGE(D3:D271) -> -5.5762082e-05 | S2: =AVERAGE(E3:E271) -> 0.00063234201 | T2: =AVERAGE(F3:F271) -> 0.0012163569 | U2: =AVERAGE(G3:G271) -> 0.0012921933 | V2: =AVERAGE(H3:H271) -> -0.00023717472 | W2: =AVERAGE(I3:I271) -> -0.00020334572 | ... Z2: =AVERAGE(L3:L271) -> 0.00028513011 | AI2: 0.0045 | AJ2: -0.0043 | AK2: 0.0377
A3: 45989 | B3: -0.0042 | C3: 0.0003 | D3: -0.0064 | E3: -0.0026 | F3: 0.0045 | G3: -0.0043 | H3: 0.0224 | I3: -0.0107 | J3: 0.0377 | K3: -0.015 | L3: -0.0005 | O3: Annualised Return | P3: =P2*250 -> 0.11784387 | Q3: =Q2*250 -> -0.22193309 | R3: =R2*250 -> -0.01394052 | S3: =S2*250 -> 0.1580855 | T3: =T2*250 -> 0.30408922 | U3: =U2*250 -> 0.32304833 | V3: =V2*250 -> -0.05929368 | W3: =W2*250 -> -0.050836431 | X3: =X2*250 -> 0.49572491 | Y3: =K275 -> 0.056598513 | Z3: =L275 -> 0.071282528 | AI3: 0.0038 | AJ3: -0.0033 | AK3: 0.0219
A4: 45988 | B4: -0.0081 | C4: -0.0083 | D4: 0.0061 | E4: -0.0068 | F4: 0.0038 | G4: -0.0033 | H4: 0.0091 | I4: 0.0108 | J4: 0.0219 | K4: -0.0044 | L4: 0.0004 | O4: Risk | P4: =_xlfn.STDEV.S(B3:B271) -> 0.01217096 | Q4: =_xlfn.STDEV.S(C3:C271) -> 0.012959634 | R4: =_xlfn.STDEV.S(D3:D271) -> 0.014540928 | S4: =_xlfn.STDEV.S(E3:E271) -> 0.013382207 | T4: =_xlfn.STDEV.S(F3:F271) -> 0.018905052 | U4: =_xlfn.STDEV.S(G3:G271) -> 0.03179231 | V4: =_xlfn.STDEV.S(H3:H271) -> 0.021611043 | W4: =_xlfn.STDEV.S(I3:I271) -> 0.02302548 | ... Z4: =_xlfn.STDEV.S(L3:L271) -> 0.0077923136 | AI4: 0.0026 | AJ4: 0.0121 | AK4: 0.026
A5: 45987 | B5: 0.0108 | C5: 0.014 | D5: -0.0032 | E5: 0.0028 | F5: 0.0026 | G5: 0.0121 | H5: 0.0165 | I5: 0.0015 | J5: 0.026 | K5: 0.0137 | L5: 0.0124 | O5: Annualised Risk | P5: =P4*SQRT(250) -> 0.19243978 | Q5: =Q4*SQRT(250) -> 0.20490981 | R5: =R4*SQRT(250) -> 0.22991226 | S5: =S4*SQRT(250) -> 0.21159127 | T5: =T4*SQRT(250) -> 0.29891512 | U5: =U4*SQRT(250) -> 0.50268055 | V5: =V4*SQRT(250) -> 0.3417006 | W5: =W4*SQRT(250) -> 0.3640648 | ... Z5: =Z4*SQRT(250) -> 0.1232073 | AI5: -0.0016 | AJ5: 0.0096 | AK5: -0.0028
A6: 45986 | B6: -0.0047 | C6: -0.007 | D6: 0.0029 | E6: 0.0072 | F6: -0.0016 | G6: 0.0096 | H6: 0.0189 | I6: 0.0037 | J6: -0.0028 | K6: -0.0292 | L6: -0.0029 | O6: Systematic Risk (Beta) | P6: =SLOPE(B3:B271,$L$3:$L$271) -> 0.71446108 | Q6: =SLOPE(C3:C271,$L$3:$L$271) -> 0.94717929 | R6: =SLOPE(D3:D271,$L$3:$L$271) -> 0.84931337 | S6: =SLOPE(E3:E271,$L$3:$L$271) -> 0.6086603 | T6: =SLOPE(F3:F271,$L$3:$L$271) -> 0.78374946 | U6: =SLOPE(G3:G271,$L$3:$L$271) -> 1.1587776 | V6: =SLOPE(H3:H271,$L$3:$L$271) -> 1.3135126 | W6: =SLOPE(I3:I271,$L$3:$L$271) -> 0.76709311 | ... Z6: =SLOPE(L3:L271,$L$3:$L$271) -> 1 | AI6: -0.0135 | AJ6: -0.0247 | AK6: -0.0055
A7: 45985 | B7: -0.009 | C7: -0.003 | D7: -0.0081 | E7: 0.0087 | F7: -0.0135 | G7: -0.0247 | H7: -0.0094 | I7: 0.0019 | J7: -0.0055 | K7: -0.0209 | L7: -0.0042 | O7: Systematic Risk (Beta^2* Market Nifty) | P7: =P6^2*($Z$5) -> 0.062891735 | Q7: =Q6^2*($Z$5) -> 0.11053525 | R7: =R6^2*($Z$5) -> 0.088873514 | S7: =S6^2*($Z$5) -> 0.045644282 | T7: =T6^2*($Z$5) -> 0.075681711 | U7: =U6^2*($Z$5) -> 0.16543851 | V7: =V6^2*($Z$5) -> 0.21257144 | W7: =W6^2*($Z$5) -> 0.072499096 | ... Z7: =Z6^2*($Z$5) -> 0.1232073 | AI7: -0.0006 | AJ7: -0.0154 | AK7: -0.0395
A8: 45982 | B8: 0.0012 | C8: 0.0018 | D8: -0.0065 | E8: -0.0094 | F8: -0.0006 | G8: -0.0154 | H8: -0.0293 | I8: -0.0123 | J8: -0.0395 | K8: 0.0018 | L8: -0.0047 | O8: Unsystematic Risk | P8: =P5-P7 -> 0.12954804 | Q8: =Q5-Q7 -> 0.094374559 | R8: =R5-R7 -> 0.14103875 | S8: =S5-S7 -> 0.16594699 | T8: =T5-T7 -> 0.22323341 | U8: =U5-U7 -> 0.33724204 | V8: =V5-V7 -> 0.12912916 | W8: =W5-W7 -> 0.2915657 | ... Z8: =Z5-Z7 -> 0 | AI8: -0.0346 | AJ8: -0.001 | AK8: -0.007
A9: 45981 | B9: 0.0002 | C9: -0.0009 | D9: -0.0063 | E9: -0.0027 | F9: -0.0346 | G9: -0.001 | H9: -0.0092 | I9: -0.0038 | J9: -0.007 | K9: 0.0223 | L9: 0.0054 | O9: Reward to Beta | P9: =(P3-6%)/P6 -> 0.080961536 | Q9: =(Q3-7%)/Q6 -> -0.30821312 | R9: =(R3-7%)/R6 -> -0.098833391 | S9: =(S3-7%)/S6 -> 0.1447203 | T9: =(T3-7%)/T6 -> 0.29867863 | U9: =(U3-7%)/U6 -> 0.21837523 | V9: =(V3-7%)/V6 -> -0.098433528 | W9: =(W3-7%)/W6 -> -0.15752512 | X9: =(X3-7%)/X6 -> 0.45443025 | Y9: =(Y3-7%)/Y6 -> -0.013045332 | AI9: 0.0131 | AJ9: 0.0138 | AK9: 0.018
A10: 45980 | B10: 0.011 | C10: 0.0196 | D10: -0.0016 | E10: -0.0157 | F10: 0.0131 | G10: 0.0138 | H10: 0.0013 | I10: 0.0021 | J10: 0.018 | K10: -0.0029 | L10: 0.0055 | O10: Rank | P10: =_xlfn.RANK.EQ(P9,$P$9:$Y$9,0) -> 5 | Q10: =_xlfn.RANK.EQ(Q9,$P$9:$Y$9,0) -> 10 | R10: =_xlfn.RANK.EQ(R9,$P$9:$Y$9,0) -> 8 | S10: =_xlfn.RANK.EQ(S9,$P$9:$Y$9,0) -> 4 | T10: =_xlfn.RANK.EQ(T9,$P$9:$Y$9,0) -> 2 | U10: =_xlfn.RANK.EQ(U9,$P$9:$Y$9,0) -> 3 | V10: =_xlfn.RANK.EQ(V9,$P$9:$Y$9,0) -> 7 | W10: =_xlfn.RANK.EQ(W9,$P$9:$Y$9,0) -> 9 | ... Y10: =_xlfn.RANK.EQ(Y9,$P$9:$Y$9,0) -> 6 | AI10: 0.0047 | AJ10: -0.0243 | AK10: -0.0467
A11: 45979 | B11: -0.0041 | C11: -0.0049 | D11: 0.0002 | E11: -0.0075 | F11: 0.0047 | G11: -0.0243 | H11: -0.0164 | I11: -0.0046 | J11: -0.0467 | K11: -0.0136 | L11: -0.004 | AI11: 0.0095 | AJ11: -0.0041 | AK11: 0.0187
A12: 45978 | B12: -0.001 | C12: -0.0012 | D12: 0.0065 | E12: -0.0032 | F12: 0.0095 | G12: -0.0041 | H12: -0.0065 | I12: 0.0077 | J12: 0.0187 | K12: 0.0176 | L12: 0.004 | O12: Parameters | P12: Return | Q12: Annualised Return | R12: Risk | S12: Annualised Risk | T12: Systematic Risk (Beta) | U12: Systematic Risk (Beta^2* Market Nifty) | V12: Unsystematic Risk | W12: Reward to Beta (Treynor Ratio) | X12: Rank | Y12: (R-Rf)*Beta/unsystematic Risk | Z12: Cumulative Beta | AA12: Beta^2/Unsystematic Risk | AB12: Cumulative | AC12: C point | AF12: Weights | AI12: -0.0245 | AJ12: 0.0136 | AK12: 0.0043
A13: 45975 | B13: -0.0028 | C13: 0.0001 | D13: 0.0073 | E13: 0.0015 | F13: -0.0245 | G13: 0.0136 | H13: -0.0165 | I13: 0.0044 | J13: 0.0043 | K13: -0.0078 | L13: 0.0012 | AI13: 0.0084 | AJ13: -0.0009 | AK13: 0.0013
A14: 45974 | B14: -0.0023 | C14: -0.0083 | D14: 0.003 | E14: 0.0004 | F14: 0.0084 | G14: -0.0009 | H14: 0.0276 | I14: -0.0141 | J14: 0.0013 | K14: 0.0265 | L14: 0.0001 | O14: CEMI | P14: 0.0019828996 | Q14: 0.49572491 | R14: 0.024901265 | S14: 0.39372357 | T14: 0.93683224 | U14: 0.10813346 | V14: 0.28559011 | W14: 0.45443025 | X14: 1 | Y14: =((Q14-7%)*T14)/V14 -> 1.3965218 | Z14: =Z13+Y14 -> 1.3965218 | AA14: =(T14^2)/V14 -> 3.0731269 | AB14: =AB13+AA14 -> 3.0731269 | AC14: =($Z$5*Z14)/(1+$Z$5*AB14) -> 0.12480613 | AD14: =IF(W14>AC14,"SELECTED","REJECTED") -> SELECTED | AE14: =((W14-$AC$13)*(T14^2))/V14 -> 1.3965218 | AF14: =AE14/$AE$24 -> 0.45226064 | AI14: 0.0166 | AJ14: 0.0054 | AK14: 0.014
A15: 45973 | B15: 0.008 | C15: 0.0278 | D15: -0.0005 | E15: -0.0003 | F15: 0.0166 | G15: 0.0054 | H15: -0.0115 | I15: 0.0034 | J15: 0.014 | K15: 0 | L15: 0.007 | O15: HYUNDAI | P15: 0.0012163569 | Q15: 0.30408922 | R15: 0.018905052 | S15: 0.29891512 | T15: 0.78374946 | U15: 0.075681711 | V15: 0.22323341 | W15: 0.29867863 | X15: 2 | Y15: =((Q15-7%)*T15)/V15 -> 0.82186309 | Z15: =Z14+Y15 -> 2.2183849 | AA15: =(T15^2)/V15 -> 2.7516635 | AB15: =AB14+AA15 -> 5.8247904 | AC15: =($Z$5*Z15)/(1+$Z$5*AB15) -> 0.15912447 | AD15: =IF(W15>AC15,"SELECTED","REJECTED") -> SELECTED | AE15: =((W15-$AC$13)*(T15^2))/V15 -> 0.82186309 | AF15: =AE15/$AE$24 -> 0.26615862 | AI15: -0.0001 | AJ15: 0.0074 | AK15: -0.0259
A16: 45972 | B16: 0.0041 | C16: 0.0072 | D16: 0.001 | E16: 0.0022 | F16: -0.0001 | G16: 0.0074 | H16: 0.006 | I16: 0.006 | J16: -0.0259 | K16: -0.0021 | L16: 0.0047 | O16: ADANI POWER | P16: 0.0012921933 | Q16: 0.32304833 | R16: 0.03179231 | S16: 0.50268055 | T16: 1.1587776 | U16: 0.16543851 | V16: 0.33724204 | W16: 0.21837523 | X16: 3 | Y16: =((Q16-7%)*T16)/V16 -> 0.86948454 | Z16: =Z15+Y16 -> 3.0878694 | AA16: =(T16^2)/V16 -> 3.9816079 | AB16: =AB15+AA16 -> 9.8063983 | AC16: =($Z$5*Z16)/(1+$Z$5*AB16) -> 0.17228722 | AD16: =IF(W16>AC16,"SELECTED","REJECTED") -> SELECTED | AE16: =((W16-$AC$13)*(T16^2))/V16 -> 0.86948454 | AF16: =AE16/$AE$24 -> 0.28158073 | AI16: 0.0129 | AJ16: -0.0094 | AK16: -0.0296
A17: 45971 | B17: 0.0002 | C17: 0.0112 | D17: -0.0265 | E17: 0.0663 | F17: 0.0129 | G17: -0.0094 | H17: 0.0213 | I17: 0.0068 | J17: -0.0296 | K17: -0.003 | L17: 0.0032 | O17: TORRENT | P17: 0.00063234201 | Q17: 0.1580855 | R17: 0.013382207 | S17: 0.21159127 | T17: 0.6086603 | U17: 0.045644282 | V17: 0.16594699 | W17: 0.1447203 | X17: 4 | Y17: =((Q17-7%)*T17)/V17 -> 0.32307997 | Z17: =Z16+Y17 -> 3.4109494 | AA17: =(T17^2)/V17 -> 2.232444 | AB17: =AB16+AA17 -> 12.038842 | AC17: =($Z$5*Z17)/(1+$Z$5*AB17) -> 0.16923384 | AD17: =IF(W17>AC17,"SELECTED","REJECTED") -> REJECTED | AI17: -0.0116 | AJ17: -0.011 | AK17: 0.0084
A18: 45968 | B18: -0.0027 | C18: -0.0063 | D18: 0.0313 | E18: 0.0075 | F18: -0.0116 | G18: -0.011 | H18: 0.0156 | I18: -0.0139 | J18: 0.0084 | K18: 0.004 | L18: -0.0007 | O18: NESTLE | P18: 0.00047137546 | Q18: 0.11784387 | R18: 0.01217096 | S18: 0.19243978 | T18: 0.71446108 | U18: 0.062891735 | V18: 0.12954804 | W18: 0.080961536 | X18: 5 | Y18: =((Q18-7%)*T18)/V18 -> 0.26386026 | Z18: =Z17+Y18 -> 3.6748097 | AA18: =(T18^2)/V18 -> 3.9402728 | AB18: =AB17+AA18 -> 15.979115 | AC18: =($Z$5*Z18)/(1+$Z$5*AB18) -> 0.1525101 | AD18: =IF(W18>AC18,"SELECTED","REJECTED") -> REJECTED | AI18: -0.0174 | AJ18: -0.033 | AK18: -0.0156
A19: 45967 | B19: 0.0009 | C19: 0.0069 | D19: -0.0106 | E19: -0.006 | F19: -0.0174 | G19: -0.033 | H19: -0.013 | I19: -0.0152 | J19: -0.0156 | K19: -0.0333 | L19: -0.0034 | O19: TATA COMM | P19: 0.00022639405 | Q19: 0.056598513 | R19: 0.018273482 | S19: 0.28892913 | T19: 1.0273014 | U19: 0.13002658 | V19: 0.15890254 | W19: -0.013045332 | X19: 6 | Y19: =((Q19-7%)*T19)/V19 -> -0.086640312 | Z19: =Z18+Y19 -> 3.5881694 | AA19: =(T19^2)/V19 -> 6.6414802 | AB19: =AB18+AA19 -> 22.620595 | AC19: =($Z$5*Z19)/(1+$Z$5*AB19) -> 0.1167378 | AD19: =IF(W19>AC19,"SELECTED","REJECTED") -> REJECTED | AI19: -0.0133 | AJ19: 0.0106 | AK19: 0.0049
A20: 45965 | B20: -0.0013 | C20: -0.0088 | D20: -0.0154 | E20: -0.0147 | F20: -0.0133 | G20: 0.0106 | H20: -0.0152 | I20: 0.0097 | J20: 0.0049 | K20: 0.0023 | L20: -0.0064 | O20: HZNC | P20: -0.00023717472 | Q20: -0.05929368 | R20: 0.021611043 | S20: 0.3417006 | T20: 1.3135126 | U20: 0.21257144 | V20: 0.12912916 | W20: -0.098433528 | X20: 7 | Y20: =((Q20-7%)*T20)/V20 -> -1.3151861 | Z20: =Z19+Y20 -> 2.2729832 | AA20: =(T20^2)/V20 -> 13.36116 | AB20: =AB19+AA20 -> 35.981756 | AC20: =($Z$5*Z20)/(1+$Z$5*AB20) -> 0.051543722 | AD20: =IF(W20>AC20,"SELECTED","REJECTED") -> REJECTED | AI20: -0.0046 | AJ20: -0.0071 | AK20: 0.0595
A21: 45964 | B21: -0.0039 | C21: -0.0135 | D21: 0.0282 | E21: 0.0192 | F21: -0.0046 | G21: -0.0071 | H21: 0.0087 | I21: -0.0161 | J21: 0.0595 | K21: 0.0137 | L21: 0.0016 | O21: LIC | P21: -5.5762082e-05 | Q21: -0.01394052 | R21: 0.014540928 | S21: 0.22991226 | T21: 0.84931337 | U21: 0.088873514 | V21: 0.14103875 | W21: -0.098833391 | X21: 8 | Y21: =((Q21-7%)*T21)/V21 -> -0.50547673 | Z21: =Z20+Y21 -> 1.7675065 | AA21: =(T21^2)/V21 -> 5.1144328 | AB21: =AB20+AA21 -> 41.096188 | AC21: =($Z$5*Z21)/(1+$Z$5*AB21) -> 0.035915737 | AD21: =IF(W21>AC21,"SELECTED","REJECTED") -> REJECTED | AI21: 0.0104 | AJ21: -0.029 | AK21: -0.0428
A22: 45961 | B22: -0.0065 | C22: 0.0075 | D22: -0.0067 | E22: -0.0117 | F22: 0.0104 | G22: -0.029 | H22: -0.0023 | I22: -0.0015 | J22: -0.0428 | K22: -0.0201 | L22: -0.006 | O22: DB CORP | P22: -0.00020334572 | Q22: -0.050836431 | R22: 0.02302548 | S22: 0.3640648 | T22: 0.76709311 | U22: 0.072499096 | V22: 0.2915657 | W22: -0.15752512 | X22: 9 | Y22: =((Q22-7%)*T22)/V22 -> -0.31791391 | Z22: =Z21+Y22 -> 1.4495926 | AA22: =(T22^2)/V22 -> 2.0181792 | AB22: =AB21+AA22 -> 43.114368 | AC22: =($Z$5*Z22)/(1+$Z$5*AB22) -> 0.02829535 | AD22: =IF(W22>AC22,"SELECTED","REJECTED") -> REJECTED | AI22: 0.0238 | AJ22: 0.0029 | AK22: 0.0004
A23: 45960 | B23: 0.0054 | C23: -0.0073 | D23: -0.0088 | E23: 0.0009 | F23: 0.0238 | G23: 0.0029 | H23: -0.0124 | I23: 0.0088 | J23: 0.0004 | K23: 0.0021 | L23: -0.0068 | O23: TCS | P23: -0.00088773234 | Q23: -0.22193309 | R23: 0.012959634 | S23: 0.20490981 | T23: 0.94717929 | U23: 0.11053525 | V23: 0.094374559 | W23: -0.30821312 | X23: 10 | Y23: =((Q23-7%)*T23)/V23 -> -2.9299525 | Z23: =Z22+Y23 -> -1.4803599 | AA23: =(T23^2)/V23 -> 9.5062549 | AB23: =AB22+AA23 -> 52.620622 | AC23: =($Z$5*Z23)/(1+$Z$5*AB23) -> -0.02437327 | AD23: =IF(W23>AC23,"SELECTED","REJECTED") -> REJECTED | AI23: 0.0257 | AJ23: -0.0014 | AK23: 0.0105
A24: 45959 | B24: 0.0016 | C24: -0.0001 | D24: 0.0098 | E24: 0.0064 | F24: 0.0257 | G24: -0.0014 | H24: 0.0263 | I24: 0.0194 | J24: 0.0105 | K24: 0.0016 | L24: 0.0045 | O24: NIFTY | P24: 0.00028513011 | Q24: 0.071282528 | R24: 0.0077923136 | S24: 0.1232073 | T24: 1 | U24: 0.1232073 | V24: 0 | AE24: =SUM(AE14:AE16) -> 3.0878694 | AI24: 0.0113 | AJ24: -0.0039 | AK24: 0.0098
A25: 45958 | B25: -0.0094 | C25: -0.0088 | D25: 0.0025 | E25: -0.0055 | F25: 0.0113 | G25: -0.0039 | H25: -0.023 | I25: -0.0338 | J25: 0.0098 | K25: -0.0178 | L25: -0.0011 | AI25: 0.0028 | AJ25: -0.0284 | AK25: 0.037
A26: 45957 | B26: 0.0008 | C26: 0.0071 | D26: 0.009 | E26: 0.0042 | F26: 0.0028 | G26: -0.0284 | H26: -0.009 | I26: 0.0413 | J26: 0.037 | K26: 0.0239 | L26: 0.0066 | P26: HYUNDAI | Q26: ADANI POWER | R26: CEMI | S26: Weights | AI26: -0.0112 | AJ26: 0.0149 | AK26: -0.0034
A27: 45954 | B27: 0.0072 | C27: -0.0033 | D27: -0.0114 | E27: -0.009 | F27: -0.0112 | G27: 0.0149 | H27: 0.0094 | I27: 0.0047 | J27: -0.0034 | K27: 0.0236 | L27: -0.0037 | O27: HYUNDAI | P27: =SQRT(VARP(Sheet2!$AI$2:$AI$270)) -> 0.01886988 | Q27: =SQRT(VARP(Sheet2!$AI$2:$AI$270)) -> 0.01886988 | R27: =SQRT(VARP(Sheet2!$AI$2:$AI$270)) -> 0.01886988 | S27: 0.45226064 | AI27: -0.0216 | AJ27: -0.0323 | AK27: 0.0056
A28: 45953 | B28: -0.0113 | C28: 0.0221 | D28: 0.0088 | E28: 0.0065 | F28: -0.0216 | G28: -0.0323 | H28: -0.0035 | I28: 0.0271 | J28: 0.0056 | K28: -0.0329 | L28: 0.0009 | O28: ADANI POWER | P28: =SQRT(VARP(Sheet2!$AI$2:$AI$270)) -> 0.01886988 | Q28: =SQRT(VARP(Sheet2!$AI$2:$AI$270)) -> 0.01886988 | R28: =SQRT(VARP(Sheet2!$AI$2:$AI$270)) -> 0.01886988 | S28: 0.26615862 | AI28: 0.0085 | AJ28: 0.0028 | AK28: -0.0006
A29: 45951 | B29: 0.0015 | C29: -0.0028 | D29: 0.0003 | E29: 0.0057 | F29: 0.0085 | G29: 0.0028 | H29: -0.0052 | I29: 0.0125 | J29: -0.0006 | K29: 0.0054 | L29: 0.001 | O29: CEMI | P29: =SQRT(VARP(Sheet2!$AI$2:$AI$270)) -> 0.01886988 | Q29: =SQRT(VARP(Sheet2!$AI$2:$AI$270)) -> 0.01886988 | R29: =SQRT(VARP(Sheet2!$AI$2:$AI$270)) -> 0.01886988 | S29: 0.28158073 | AI29: -0.0101 | AJ29: 0.026 | AK29: 0.0333
A30: 45950 | B30: -0.0032 | C30: 0.0179 | D30: 0.0072 | E30: -0.0039 | F30: -0.0101 | G30: 0.026 | H30: -0.0277 | I30: 0.0185 | J30: 0.0333 | K30: -0.0113 | L30: 0.0052 | Q30: Annualised Risk | AI30: -0.0048 | AJ30: 0.0547 | AK30: 0.0011
A31: 45947 | B31: 0.0101 | C31: -0.0029 | D31: -0.0097 | E31: 0.0143 | F31: -0.0048 | G31: 0.0547 | H31: -0.0127 | I31: 0.005 | J31: 0.0011 | K31: -0.0225 | L31: 0.0049 | O31: PORTFOLIO RISK | P31: {=MMULT(TRANSPOSE(S27:S29),MMULT(P27:R29,S27:S29))} -> 0.01886988 | Q31: =P31*SQRT(250) -> 0.298359 | AI31: -0.0254 | AJ31: -0.0009 | AK31: -0.0207
A32: 45946 | B32: 0.0452 | C32: 0.0003 | D32: -0.0053 | E32: 0.0003 | F32: -0.0254 | G32: -0.0009 | H32: -0.0127 | I32: 0.0113 | J32: -0.0207 | K32: 0.0083 | L32: 0.0103 | AI32: 0.0032 | AJ32: 0.0168 | AK32: 0.0291
A33: 45945 | B33: 0.039 | C33: 0.0032 | D33: -0.0034 | E33: 0.0031 | F33: 0.0032 | G33: 0.0168 | H33: 0.0149 | I33: -0.0842 | J33: 0.0291 | K33: 0.0441 | L33: 0.0071 | AI33: 0.0117 | AJ33: 0.003 | AK33: -0.0472
A34: 45944 | B34: -0.0106 | C34: -0.0156 | D34: 0.0053 | E34: 0.0011 | F34: 0.0117 | G34: 0.003 | H34: 0.0002 | I34: -0.0102 | J34: -0.0472 | K34: 0.0414 | L34: -0.0032 | AI34: -0.0089 | AJ34: 0.0316 | AK34: -0.0174
A35: 45943 | B35: -0.0095 | C35: -0.007 | D35: -0.0006 | E35: -0.0041 | F35: -0.0089 | G35: 0.0316 | H35: 0.0145 | I35: -0.0109 | J35: -0.0174 | K35: -0.0385 | L35: -0.0023 | AI35: -0.0015 | AJ35: 0.0053 | AK35: 0.0123
A36: 45940 | B36: 0.0099 | C36: -0.0109 | D36: 0.0029 | E36: -0.005 | F36: -0.0015 | G36: 0.0053 | H36: -0.0272 | I36: 0.0085 | J36: 0.0123 | K36: 0.1022 | L36: 0.0041 | AI36: -0.0263 | AJ36: 0.0009 | AK36: -0.0023
A37: 45939 | B37: 0.0062 | C37: 0.0114 | D37: 0.0016 | E37: -0.0052 | F37: -0.0263 | G37: 0.0009 | H37: 0.0443 | I37: 0.0128 | J37: -0.0023 | K37: 0.0045 | L37: 0.0054 | AI37: 0.0079 | AJ37: -0.0178 | AK37: -0.0206
A38: 45938 | B38: 0.0031 | C38: 0.018 | D38: -0.0203 | E38: 0.0091 | F38: 0.0079 | G38: -0.0178 | H38: 0.0012 | I38: -0.0248 | J38: -0.0206 | K38: 0.0161 | L38: -0.0025 | AI38: -0.0106 | AJ38: -0.0034 | AK38: -0.0223
A39: 45937 | B39: -0.0041 | C39: -0.0049 | D39: 0.0057 | E39: 0.0031 | F39: -0.0106 | G39: -0.0034 | H39: -0.0033 | I39: 0.01 | J39: -0.0223 | K39: 0.0024 | L39: 0.0012 | AI39: -0.0107 | AJ39: 0.0313 | AK39: 0.0323
A40: 45936 | B40: 0.0101 | C40: 0.0298 | D40: 0.0021 | E40: 0.0032 | F40: -0.0107 | G40: 0.0313 | H40: 0 | I40: -0.0093 | J40: 0.0323 | K40: 0.0277 | L40: 0.0074 | AI40: -0.0117 | AJ40: -0.0336 | AK40: 0.005
A41: 45933 | B41: 0.003 | C41: -0.0042 | D41: 0.0013 | E41: -0.0147 | F41: -0.0117 | G41: -0.0336 | H41: 0.0211 | I41: -0.0056 | J41: 0.005 | K41: 0.0004 | L41: 0.0023 | AI41: -0.0183 | AJ41: 0.0543 | AK41: 0.0062
A42: 45931 | B42: 0.0117 | C42: 0.0089 | D42: 0.0042 | E42: -0.01 | F42: -0.0183 | G42: 0.0543 | H42: -0.0023 | I42: 0.0006 | J42: 0.0062 | K42: -0.0001 | L42: 0.0092 | AI42: -0.0218 | AJ42: -0.0136 | AK42: 0.0381
A43: 45930 | B43: 0.0003 | C43: -0.0027 | D43: 0.0059 | E43: 0.0046 | F43: -0.0218 | G43: -0.0136 | H43: 0.035 | I43: 0.0088 | J43: 0.0381 | K43: 0.0002 | L43: -0.001 | AI43: 0.0011 | AJ43: 0.0027 | AK43: -0.0261
... A270: 45596 | B270: -0.0059 | C270: -0.0284 | D270: -0.0127 | E270: 0.0207 | F270: -0.0052 | G270: 0.0011 | H270: -0.0128 | I270: 0.0773 | J270: 0.008 | K270: -0.007 | L270: -0.0056 | AI270: 0.0418 | AJ270: -0.0004 | AK270: 0.0486
A271: 45595 | B271: 0.0039 | C271: 0.0023 | D271: 0.0006 | E271: -0.0242 | F271: 0.0418 | G271: -0.0004 | H271: 0.0186 | I271: 0.0221 | J271: 0.0486 | K271: 0.0017 | L271: -0.0051
A273: Parameters | B273: NESTLE | C273: TCS | D273: LIC | E273: TORRENT | F273: HYUNDAI | G273: ADANI POWER | H273: HZNC | I273: DB CORP | J273: CEMI | K273: TATA COMM | L273: NIFTY
A274: Return | B274: =AVERAGE(B3:B271) -> 0.00047137546 | C274: =AVERAGE(C3:C271) -> -0.00088773234 | D274: =AVERAGE(D3:D271) -> -5.5762082e-05 | E274: =AVERAGE(E3:E271) -> 0.00063234201 | F274: =AVERAGE(F3:F271) -> 0.0012163569 | G274: =AVERAGE(G3:G271) -> 0.0012921933 | H274: =AVERAGE(H3:H271) -> -0.00023717472 | I274: =AVERAGE(I3:I271) -> -0.00020334572 | ... L274: =AVERAGE(L3:L271) -> 0.00028513011
A275: Annualised Return | B275: =B274*250 -> 0.11784387 | C275: =C274*250 -> -0.22193309 | D275: =D274*250 -> -0.01394052 | E275: =E274*250 -> 0.1580855 | F275: =F274*250 -> 0.30408922 | G275: =G274*250 -> 0.32304833 | H275: =H274*250 -> -0.05929368 | I275: =I274*250 -> -0.050836431 | ... L275: =L274*250 -> 0.071282528
A276: Risk | B276: =_xlfn.STDEV.S(B3:B271) -> 0.01217096 | C276: =_xlfn.STDEV.S(C3:C271) -> 0.012959634 | D276: =_xlfn.STDEV.S(D3:D271) -> 0.014540928 | E276: =_xlfn.STDEV.S(E3:E271) -> 0.013382207 | F276: =_xlfn.STDEV.S(F3:F271) -> 0.018905052 | G276: =_xlfn.STDEV.S(G3:G271) -> 0.03179231 | H276: =_xlfn.STDEV.S(H3:H271) -> 0.021611043 | I276: =_xlfn.STDEV.S(I3:I271) -> 0.02302548 | ... L276: =_xlfn.STDEV.S(L3:L271) -> 0.0077923136
A277: Annualised Risk | B277: =B276*SQRT(250) -> 0.19243978 | C277: =C276*SQRT(250) -> 0.20490981 | D277: =D276*SQRT(250) -> 0.22991226 | E277: =E276*SQRT(250) -> 0.21159127 | F277: =F276*SQRT(250) -> 0.29891512 | G277: =G276*SQRT(250) -> 0.50268055 | H277: =H276*SQRT(250) -> 0.3417006 | I277: =I276*SQRT(250) -> 0.3640648 | ... L277: =L276*SQRT(250) -> 0.1232073

Sheet Sheet3
C3: Stock | D3: Weights | E3: Annualised Return | F3: Portfolio RETURN | H3: Unsystematic Beta
C4: CEMI | D4: 0.45226064 | E4: =Sheet2!X3 -> 0.49572491 | F4: =SUMPRODUCT(D4:D6,E4:E6) -> 0.39609702 | H4: =Sheet2!V14 -> 0.28559011
C5: HYUNDAI | D5: 0.26615862 | E5: =Sheet2!T3 -> 0.30408922 | H5: =Sheet2!V15 -> 0.22323341
C6: ADANI POWER | D6: 0.28158073 | E6: =Sheet2!U3 -> 0.32304833 | H6: =Sheet2!V16 -> 0.33724204
G7: Portfolio Beta | H7: =AVERAGE(H4:H6) -> 0.28202185
C8: Portfolio Return | D8: =F4 -> 0.39609702
C9: Portfolio RISK | D9: =Sheet2!Q31 -> 0.298359
C10: utility | D10: =D8/D9 -> 1.3275853
C13: Sharpe Ratio | D13: =(D8-6%)/D9 -> 1.1264853
C14: Treynor Ratio | D14: =(D8-6%)/H7 -> 1.191741
C15: Alpha | D15: =(D8-(6%+(1-H7)*Sheet2!Z3)) -> 0.28491772
